app_name_function/.env
app_name_function/.env.prod
app_name_function/.env.sample
app_name_function/Dockerfile
app_name_function/README.md
app_name_function/requirements.txt
app_name_function/src/__init__.py
app_name_function/src/main.py
app_name_function/src/api/__init__.py
app_name_function/src/api/v1/__init__.py
app_name_function/src/api/v1/routers.py
app_name_function/src/api/v1/endpoints/__init__.py
app_name_function/src/api/v1/endpoints/items.py
app_name_function/src/api/v1/endpoints/users.py
app_name_function/src/core/__init__.py
app_name_function/src/core/config.py
app_name_function/src/core/security.py
app_name_function/src/db/__init__.py
app_name_function/src/db/session.py
app_name_function/src/db/repositories/item_db.py
app_name_function/src/db/repositories/user_db.py
app_name_function/src/models/__init__.py
app_name_function/src/models/db_models.py
app_name_function/src/models/schemas.py
app_name_function/src/services/__init__.py
app_name_function/src/services/item_service.py
app_name_function/src/services/user_service.py
app_name_function/src/utils/__init__.py
app_name_function/src/utils/helpers.py
app_name_function/src/utils/logger.py
app_name_function/static/images/favicon.ico
app_name_function/tests/__init__.py
app_name_function/tests/conftest.py
app_name_function/tests/test_xx.py
app_name_module/.env
app_name_module/.env.prod
app_name_module/Dockerfile
app_name_module/README.md
app_name_module/requirements.txt
app_name_module/src/__init__.py
app_name_module/src/main.py
app_name_module/src/core/__init__.py
app_name_module/src/core/config.py
app_name_module/src/core/dependencies.py
app_name_module/src/core/security.py
app_name_module/src/modules/auth/__init__.py
app_name_module/src/modules/auth/dependencies.py
app_name_module/src/modules/auth/models.py
app_name_module/src/modules/auth/repositories.py
app_name_module/src/modules/auth/routers.py
app_name_module/src/modules/auth/schemas.py
app_name_module/src/modules/auth/services.py
fastapi_cli_generator-0.4.3.dist-info/licenses/LICENSE
fastapi_cli_generator-0.4.3.dist-info/METADATA
fastapi_cli_generator-0.4.3.dist-info/WHEEL
fastapi_cli_generator-0.4.3.dist-info/entry_points.txt
fastapi_cli_generator-0.4.3.dist-info/top_level.txt
fastapi_cli_generator-0.4.3.dist-info/RECORD
