Metadata-Version: 2.4
Name: fastapi-cli-generator
Version: 0.4.3
Summary: A command-line tool for generating FastAPI projects with different architectural patterns
Author-email: xukache <2416695482@qq.com>
License: MIT
Project-URL: Homepage, https://github.com/xukache/fastapi-cli-generator
Project-URL: Repository, https://github.com/xukache/fastapi-cli-generator
Project-URL: Documentation, https://github.com/xukache/fastapi-cli-generator#readme
Project-URL: Bug Tracker, https://github.com/xukache/fastapi-cli-generator/issues
Keywords: fastapi,cli,generator,scaffold,template
Classifier: Development Status :: 4 - Beta
Classifier: Intended Audience :: Developers
Classifier: License :: OSI Approved :: MIT License
Classifier: Programming Language :: Python :: 3
Classifier: Programming Language :: Python :: 3.8
Classifier: Programming Language :: Python :: 3.9
Classifier: Programming Language :: Python :: 3.10
Classifier: Programming Language :: Python :: 3.11
Classifier: Programming Language :: Python :: 3.12
Classifier: Topic :: Software Development :: Code Generators
Classifier: Topic :: Software Development :: Libraries :: Application Frameworks
Requires-Python: >=3.10
License-File: LICENSE
Requires-Dist: typer
Requires-Dist: rich
Requires-Dist: jinja2
Requires-Dist: pydantic
Requires-Dist: questionary
Provides-Extra: dev
Requires-Dist: pytest>=7.0.0; extra == "dev"
Requires-Dist: pytest-cov>=4.0.0; extra == "dev"
Requires-Dist: black>=23.0.0; extra == "dev"
Requires-Dist: isort>=5.12.0; extra == "dev"
Requires-Dist: flake8>=6.0.0; extra == "dev"
Requires-Dist: mypy>=1.0.0; extra == "dev"
Dynamic: license-file
